Workbook
Name \e: #REF!
Name \e: #REF!
Name \l: #REF!
Name \l: #REF!
Name _\e: #REF!
Name _\l: #REF!
Name __________MCV2: [1]Vehicles!$B$58:$O$58
Name _________MCV2: [1]Vehicles!$B$58:$O$58
Name ________MCV2: [1]Vehicles!$B$58:$O$58
Name _______MCV2: [1]Vehicles!$B$58:$O$58
Name ______MCV2: [1]Vehicles!$B$58:$O$58
Name _____MCV2: [1]Vehicles!$B$58:$O$58
Name ____MCV2: [1]Vehicles!$B$58:$O$58
Name ___LL100: #REF!
Name ___MCV2: [1]Vehicles!$B$58:$O$58
Name __MCV2: [1]Vehicles!$B$58:$O$58
Name _2: #REF!
Name _2_US_Fixed_TV_Pricing_W25_49: #REF!
Name _3: #REF!
Name _clb07: #REF!
Name _clb07: #REF!
Name _clp07: #REF!
Name _clp07: #REF!
Name _LL100: #REF!
Name _MCV2: [1]Vehicles!$B$58:$O$58
Name _Pos1: '[2]Data CpGRP'!$A$41
Name _Pos2: '[2]Data CpGRP'!$A$42
Name _Pos3: '[2]Data CpGRP'!$A$43
Name _Pos4: '[2]Data CpGRP'!$A$44
Name _Pos5: '[2]Data CpGRP'!$A$45
Name _Pos6: '[2]Data CpGRP'!$A$46
Name _Pos7: '[2]Data CpGRP'!$A$47
Name _Pos8: '[2]Data CpGRP'!$A$48
Name aa: #REF!
Name ab: #REF!
Name Abfrage_KW18: #REF!
Name Abfrage_KW18: #REF!
Name ac: #REF!
Name ac: #REF!
Name ad: '[3]cic 22-9 - 26-10'!$D$11
Name Adformat: [4]FormatSpecs!$B$1:$B$71
Name adresse1Vermarkter: [5]SitesVermarkter!#REF!
Name Adserverimplementierung: [4]Basisdaten!$H$8:$H$18
Name aggregate_tag: #REF!
Name aggregate_tag: #REF!
Name Aggregated_spec: #REF!
Name Aggregated_spec: #REF!
Name Alti: [7]!Alti
Name Alti: [7]!Alti
Name Alti: [7]!Alti
Name Alti: [7]!Alti
Name Alti: [7]!Alti
Name Alti: [7]!Alti
Name Alti: [7]!Alti
Name Alti: [7]!Alti
Name Alti: [7]!Alti
Name apr: #REF!
Name apr: #REF!
Name apr: #REF!
Name area: #REF!,#REF!,#REF!,#REF!,#REF!,#REF!,#REF!,#REF!,#REF!,#REF!,#REF!,#REF!,#REF!,#REF!,#REF!,#REF!,#REF!,#REF!,#REF!,#REF!,#REF!,#REF!,#REF!,#REF!

Sheet Total
C2: Клиент | D2: TBC
C3: Проект | D3: Размещение наружной рекламы в Узбекистане
C4: Контактное лицо
C5: Дата | D5: 22.01.2026
C6: Карта | D6: https://yandex.uz/maps/10335/tashkent/?ll=69.280761%2C41.308950&mode=usermaps&source=constructorLink&um=constructor%3A5e2a584d1791b34631c6666a753435b6a05652157f1241463242030e8249cf9c&z=12.52
E10: LED Ташкент | F10: LED Регионы | G10: LED Остановки | H10: Статика Таш + Регионы | I10: Аэропорт | J10: Автобусы | K10: Поезда | L10: Итого в UZS | M10: Итого в RUB
D11: Total без АК и НДС | E11: ='LED Ташкент'!R61 -> 1003309800 | F11: ='LED Регионы'!U99 -> 987120000 | G11: ='LED Остановки '!T21 -> 52200000 | H11: ='Статика Таш + Регионы'!S83 -> 523840000 | I11: =Аэропорт!T13 -> 472620000 | J11: =Автобусы!R14 -> 358575000 | K11: =Поезда!Q11 -> 115200000 | L11: =SUM(E11:K11) -> 3512864800 | M11: =L11/140 -> 25091891
D12: АК 5% | E12: =E11*5% -> 50165490 | F12: =F11*5% -> 49356000 | G12: =G11*5% -> 2610000 | H12: =H11*5% -> 26192000 | I12: =I11*5% -> 23631000 | J12: =J11*5% -> 17928750 | K12: =K11*5% -> 5760000 | L12: =L11*5% -> 175643240 | M12: =M11*5% -> 1254594.6
D13: Итоговая сумма с АК и НДС | E13: =(E11+E12)*1.12 -> 1.1798923e+09 | F13: =(F11+F12)*1.12 -> 1160853120 | G13: =(G11+G12)*1.12 -> 61387200 | H13: =(H11+H12)*1.12 -> 616035840 | I13: =(I11+I12)*1.12 -> 555801120 | J13: =(J11+J12)*1.12 -> 4.216842e+08 | K13: =(K11+K12)*1.12 -> 135475200 | L13: =(L11+L12)*1.12 -> 4.131129e+09 | M13: =(M11+M12)*1.12 -> 29508064 | N13: 29508064

Sheet LED Ташкент
C2: Клиент | D2: TBC
C3: Проект | D3: Размещение наружной рекламы в Узбекистане
C4: Дата | D4: 22.01.2026
C5: Дата
T6: плановые охваты
A7: Тип Внешней Рекламы | B7: Фото конструкции | C7: Город | D7: Адрес расположения | E7: Размер конструкции | F7: Кол-во носителей | G7: Период размещения | H7: Разрешение | I7: Длительность ролика | J7: Время работы | K7: Кол-во выходов в блоке | L7: Прогнозное кол-во выходов в сутки | M7: Стоимость за 1 единицу (без АК и НДС) | N7: Цена с учетом скидки | O7: Цена с учетом скидки в RUB | P7: Стоимость за 1 единицу (без АК и НДС) февраль | Q7: Стоимость за 1 единицу (без АК и НДС) март | R7: Общая сумма (без АК и НДС) | S7: Total без НДС в RUB | T7: ots | U7: rating | V7: universe
A8: LED - экран | B8: Фото | C8: Ташкент | D8: ТЦ Samarkand Darvoza | E8: 10х11,5 | F8: 1 | G8: 2 | H8: 1160х1400 | I8: 10 | J8: 7:00-23:00 | K8: 1 | L8: 100-200 | M8: 16830000 | N8: 15147000 | O8: =N8/140 -> 108192.86 | P8: =N8 -> 15147000 | Q8: =N8 -> 15147000 | R8: =P8+Q8 -> 30294000 | S8: =R8/140 -> 216385.71 | T8: 634849 | U8: 65.037475 | V8: 976128
A9: LED - экран | B9: Фото | C9: Ташкент | D9: пр. Буньедкор, ор. Дворец дружбы народов | E9: 18х7 | F9: 1 | G9: 2 | H9: 1800х700 | I9: 10 | J9: 7:00-23:00 | K9: 1 | L9: 100-200 | M9: 25000000 | N9: 23000000 | O9: =N9/140 -> 164285.71 | P9: =N9 -> 23000000 | Q9: =N9 -> 23000000 | R9: =P9+Q9 -> 46000000 | S9: =R9/140 -> 328571.43 | T9: 1648853 | U9: 168.9177 | V9: 976128
A10: LED - экран | B10: Фото | C10: Ташкент | D10: ул. Буюк Ипак Йули, перекресток возле метро | E10: 19х8 | F10: 1 | G10: 2 | H10: 2432х1024 | I10: 10 | J10: 7:00-23:00 | K10: 1 | L10: 100-200 | M10: 28314000 | N10: 23500620 | O10: =N10/140 -> 167861.57 | P10: =N10 -> 23500620 | Q10: =N10 -> 23500620 | R10: =P10+Q10 -> 47001240 | S10: =R10/140 -> 335723.14 | T10: 572873 | U10: 58.688307 | V10: 976128
A11: LED - экран | B11: Фото | C11: Ташкент | D11: Шахристанская, Корзинка | E11: 8х4 | F11: 1 | G11: 2 | H11: 1920х1080 | I11: 10 | J11: 7:00-23:00 | K11: 1 | L11: 100-200 | M11: 7200000 | N11: 6120000 | O11: =N11/140 -> 43714.286 | P11: =N11 -> 6120000 | Q11: =N11 -> 6120000 | R11: =P11+Q11 -> 12240000 | S11: =R11/140 -> 87428.571 | T11: 614953 | U11: 62.999217 | V11: 976128
A12: LED - экран | B12: Фото | C12: Ташкент | D12: ул Нукусская, ор перекрёсток винзавод | E12: 12х6 | F12: 1 | G12: 2 | H12: 1536х768 | I12: 10 | J12: 7:00-23:00 | K12: 1 | L12: 100-200 | M12: 19300000 | N12: 16019000 | O12: =N12/140 -> 114421.43 | P12: =N12 -> 16019000 | Q12: =N12 -> 16019000 | R12: =P12+Q12 -> 32038000 | S12: =R12/140 -> 228842.86 | T12: 736094 | U12: 75.409577 | V12: 976128
A13: LED - экран | B13: Фото | C13: Ташкент | D13: ул. Себзар, перекресток рядом с ТРЦ Riviera | E13: 10х4 | F13: 1 | G13: 2 | H13: 1800х700 | I13: 10 | J13: 7:00-23:00 | K13: 1 | L13: 100-200 | M13: 10000000 | N13: 9000000 | O13: =N13/140 -> 64285.714 | P13: =N13 -> 9000000 | Q13: =N13 -> 9000000 | R13: =P13+Q13 -> 18000000 | S13: =R13/140 -> 128571.43 | T13: 613606 | U13: 62.861223 | V13: 976128
A14: LED - экран | B14: Фото | C14: Ташкент | D14: пр. А. Тимура, гостиница City Palace | E14: 8х4 | F14: 1 | G14: 2 | H14: 720х360 | I14: 10 | J14: 7:00-23:00 | K14: 1 | L14: 100-200 | M14: 7100000 | N14: 6035000 | O14: =N14/140 -> 43107.143 | P14: =N14 -> 6035000 | Q14: =N14 -> 6035000 | R14: =P14+Q14 -> 12070000 | S14: =R14/140 -> 86214.286 | T14: 401409 | U14: 41.122578 | V14: 976128
A15: LED - экран | B15: Фото | C15: Ташкент | D15: ул. Мирзо Улугбека, Ашхабад | E15: 9х4 | F15: 1 | G15: 2 | H15: 1800х700 | I15: 10 | J15: 7:00-23:00 | K15: 1 | L15: 100-200 | M15: 11000000 | N15: 9350000 | O15: =N15/140 -> 66785.714 | P15: =N15 -> 9350000 | Q15: =N15 -> 9350000 | R15: =P15+Q15 -> 18700000 | S15: =R15/140 -> 133571.43 | T15: 276604 | U15: 28.336857 | V15: 976128
A16: LED - экран | B16: Фото | C16: Ташкент | D16: ул. Шахрисабз, ор. Автодорожный университет | E16: 9х5 | F16: 1 | G16: 2 | H16: 960х480 | I16: 10 | J16: 7:00-23:00 | K16: 1 | L16: 100-200 | M16: 7100000 | N16: 5680000 | O16: =N16/140 -> 40571.429 | P16: =N16 -> 5680000 | Q16: =N16 -> 5680000 | R16: =P16+Q16 -> 11360000 | S16: =R16/140 -> 81142.857 | T16: 650004 | U16: 66.590037 | V16: 976128
A17: LED - экран | B17: Фото | C17: Ташкент | D17: (ГУМ) район пресечение улиц Самарканд Дарвоза и Беруний | E17: 6х3 | F17: 1 | G17: 2 | H17: 1920х1080 | I17: 10 | J17: 7:00-23:00 | K17: 1 | L17: 100-200 | M17: 7000000 | N17: 5950000 | O17: =N17/140 -> 42500 | P17: =N17 -> 5950000 | Q17: =N17 -> 5950000 | R17: =P17+Q17 -> 11900000 | S17: =R17/140 -> 85000 | T17: 557369 | U17: 57.099991 | V17: 976128
A18: LED - экран | B18: Фото | C18: Ташкент | D18: ул. Фархадская, ор. Фархадский рынок, Korzinka | E18: 9х4 | F18: 1 | G18: 2 | H18: 960х480 | I18: 10 | J18: 7:00-23:00 | K18: 1 | L18: 100-200 | M18: 7100000 | N18: 5680000 | O18: =N18/140 -> 40571.429 | P18: =N18 -> 5680000 | Q18: =N18 -> 5680000 | R18: =P18+Q18 -> 11360000 | S18: =R18/140 -> 81142.857 | T18: 527048 | U18: 53.993739 | V18: 976128
A19: LED - экран | B19: Фото | C19: Ташкент | D19: пр. Ш. Рашидова, на стороне гостиницы Lotte Hotel | E19: 6х3 | F19: 1 | G19: 2 | H19: 1024х512 | I19: 10 | J19: 7:00-23:00 | K19: 1 | L19: 100-200 | M19: 15180000 | N19: 12599400 | O19: =N19/140 -> 89995.714 | P19: =N19 -> 12599400 | Q19: =N19 -> 12599400 | R19: =P19+Q19 -> 25198800 | S19: =R19/140 -> 179991.43 | T19: 328484 | U19: 33.651734 | V19: 976128
... A60: LED - экран | B60: Фото | C60: Ташкент | D60: (Лабзак) Шайхонтохурский район пересечение улиц Зулфияхоним | E60: 6х3 | F60: 1 | G60: 2 | H60: 720x360 | I60: 10 | J60: 7:00-23:00 | K60: 1 | L60: 100-200 | M60: 5700000 | N60: 4845000 | O60: =N60/140 -> 34607.143 | P60: =N60 -> 4845000 | Q60: =N60 -> 4845000 | R60: =P60+Q60 -> 9690000 | S60: =R60/140 -> 69214.286 | T60: 377102 | U60: 38.632433 | V60: 976128
M61: =SUM(M8:M60) -> 582965000 | N61: =SUM(N8:N60) -> 501654900 | O61: =SUM(O8:O60) -> 3583249.3 | P61: =SUM(P8:P60) -> 501654900 | Q61: =SUM(Q8:Q60) -> 501654900 | R61: =SUM(R8:R60) -> 1003309800 | S61: =SUM(S8:S60) -> 7166498.6

Sheet LED Регионы
C2: Клиент | D2: TBC
C3: Проект | D3: Размещение наружной рекламы в Узбекистане
C4: Дата | D4: 22.01.2026
A8: Тип Внешней Рекламы | B8: Фото конструкции | C8: Город | D8: Адрес расположения | E8: Размер конструкции | F8: Кол-во носителей | G8: Период размещения | H8: Тип конструкции | I8: Формат размещения (статика/ динамика) | J8: Разрешение | K8: Длительность ролика | L8: Время работы | M8: Кол-во выходов в блоке | N8: Прогнозное Кол-во выходов в сутки | O8: id | P8: Стоимость за 1 единицу (без НДС) на 2026 год | Q8: Цена с учетом скидки | R8: Цена с учетом скидки в RUB | S8: Стоимость за 1 единицу (без АК и НДС) февраль | T8: Стоимость за 1 единицу (без АК и НДС) март | U8: Общая сумма (без АК и НДС) | V8: Total без НДС в RUB | W8: Подрядчик по размещению | X8: ots | Y8: rating | Z8: universe
A9: LED - экран | B9: Фото | C9: Наманган | D9: ул.имени Каримова, ориентир: Микрорайон | E9: 7х4 | F9: 1 | G9: 2 | H9: экран | I9: динамика | J9: 1920х1080 | K9: 10 | L9: 7:00-23:00 | M9: 2 | N9: 100-200 | O9: 1807 | P9: 3500000 | Q9: =P9*(1-28%) -> 2520000 | R9: =Q9/140 -> 18000 | S9: =Q9*M9 -> 5040000 | T9: =Q9*M9 -> 5040000 | U9: =S9+T9 -> 10080000 | V9: =U9/140 -> 72000 | W9: Ledokol Group | X9: 199508 | Y9: 108.45773 | Z9: 183950
A10: LED - экран | B10: Фото | C10: Наманган | D10: ул. Гирвонсой Ориентир Парк Афсона | E10: 7х4 | F10: 1 | G10: 2 | H10: экран | I10: динамика | J10: 1920х1080 | K10: 10 | L10: 7:00-23:00 | M10: 2 | N10: 100-200 | O10: 7137 | P10: 3500000 | Q10: =P10*(1-28%) -> 2520000 | R10: =Q10/140 -> 18000 | S10: =Q10*M10 -> 5040000 | T10: =Q10*M10 -> 5040000 | U10: =S10+T10 -> 10080000 | V10: =U10/140 -> 72000 | W10: Ledokol Group | X10: 173640 | Y10: 94.395216 | Z10: 183950
A11: LED - экран | B11: Фото | C11: Наманган | D11: ул. А.Навои Ориентир Рынок Чорсу | E11: 7х4 | F11: 1 | G11: 2 | H11: экран | I11: динамика | J11: 1920х1080 | K11: 10 | L11: 7:00-23:00 | M11: 2 | N11: 100-200 | O11: 1802 | P11: 3500000 | Q11: =P11*(1-28%) -> 2520000 | R11: =Q11/140 -> 18000 | S11: =Q11*M11 -> 5040000 | T11: =Q11*M11 -> 5040000 | U11: =S11+T11 -> 10080000 | V11: =U11/140 -> 72000 | W11: Ledokol Group | X11: 216890 | Y11: 117.90704 | Z11: 183950
A12: LED - экран | B12: Фото | C12: Наманган | D12: ул. И. Каримова и А. Темура Ориентир Lagman House | E12: 6х3 | F12: 1 | G12: 2 | H12: экран | I12: динамика | J12: 1920х1080 | K12: 10 | L12: 7:00-23:00 | M12: 2 | N12: 100-200 | O12: 10403 | P12: 3500000 | Q12: =P12*(1-28%) -> 2520000 | R12: =Q12/140 -> 18000 | S12: =Q12*M12 -> 5040000 | T12: =Q12*M12 -> 5040000 | U12: =S12+T12 -> 10080000 | V12: =U12/140 -> 72000 | W12: Ledokol Group | X12: 265228 | Y12: 144.18483 | Z12: 183950
A13: LED - экран | B13: Фото | C13: Наманган | D13: пересечение улиц Н.Номонгони и ул.Б.Машраб, ориентир УВД, 1я поликлиника | E13: 6х3 | F13: 1 | G13: 2 | H13: экран | I13: динамика | J13: 1920х1080 | K13: 10 | L13: 7:00-23:00 | M13: 2 | N13: 100-200 | O13: 7197 | P13: 3500000 | Q13: =P13*(1-28%) -> 2520000 | R13: =Q13/140 -> 18000 | S13: =Q13*M13 -> 5040000 | T13: =Q13*M13 -> 5040000 | U13: =S13+T13 -> 10080000 | V13: =U13/140 -> 72000 | W13: Ledokol Group | X13: 168553 | Y13: 91.629791 | Z13: 183950
A14: LED - экран | B14: Фото | C14: Наманган | D14: ул. А.Навои и проспект Бабура Ориентир Молодежный центр | E14: 7х4 | F14: 1 | G14: 2 | H14: экран | I14: динамика | J14: 1920х1080 | K14: 10 | L14: 7:00-23:00 | M14: 2 | N14: 100-200 | O14: 18973 | P14: 3500000 | Q14: =P14*(1-28%) -> 2520000 | R14: =Q14/140 -> 18000 | S14: =Q14*M14 -> 5040000 | T14: =Q14*M14 -> 5040000 | U14: =S14+T14 -> 10080000 | V14: =U14/140 -> 72000 | W14: Ledokol Group | X14: 246205 | Y14: 133.84344 | Z14: 183950
A15: LED - экран | B15: Фото | C15: Наманган | D15: перекрёсток ул.Кокандская и А.Наваи, ориентир рынок Сардоба | E15: 8х4 | F15: 1 | G15: 2 | H15: экран | I15: динамика | J15: 1920х1080 | K15: 10 | L15: 7:00-23:00 | M15: 2 | N15: 100-200 | O15: 1796 | P15: 3500000 | Q15: =P15*(1-28%) -> 2520000 | R15: =Q15/140 -> 18000 | S15: =Q15*M15 -> 5040000 | T15: =Q15*M15 -> 5040000 | U15: =S15+T15 -> 10080000 | V15: =U15/140 -> 72000 | W15: Ledokol Group | X15: 273731 | Y15: 148.80728 | Z15: 183950
A16: LED - экран | B16: Фото | C16: Наманган | D16: ул. И.Каримова и Оромгох Ориентир Рынок Дустлик | E16: 7х4 | F16: 1 | G16: 2 | H16: экран | I16: динамика | J16: 1920х1080 | K16: 10 | L16: 7:00-23:00 | M16: 2 | N16: 100-200 | O16: 10715 | P16: 3500000 | Q16: =P16*(1-28%) -> 2520000 | R16: =Q16/140 -> 18000 | S16: =Q16*M16 -> 5040000 | T16: =Q16*M16 -> 5040000 | U16: =S16+T16 -> 10080000 | V16: =U16/140 -> 72000 | W16: Ledokol Group | X16: 233247 | Y16: 126.79913 | Z16: 183950
A17: LED - экран | B17: Фото | C17: Наманган | D17: ул. Туракурган и ул. А. Наваи Ориентир ШОДЛИК | E17: 6х3 | F17: 1 | G17: 2 | H17: экран | I17: динамика | J17: 1920х1080 | K17: 10 | L17: 7:00-23:00 | M17: 2 | N17: 100-200 | O17: 7372 | P17: 3500000 | Q17: =P17*(1-28%) -> 2520000 | R17: =Q17/140 -> 18000 | S17: =Q17*M17 -> 5040000 | T17: =Q17*M17 -> 5040000 | U17: =S17+T17 -> 10080000 | V17: =U17/140 -> 72000 | W17: Ledokol Group | X17: 228959 | Y17: 124.46806 | Z17: 183950
A18: LED - экран | B18: Фото | C18: Наманган | D18: перекрёсток ул.Галаба и Хотира, ориентир Макро | E18: 6х3 | F18: 1 | G18: 2 | H18: экран | I18: динамика | J18: 1920х1080 | K18: 10 | L18: 7:00-23:00 | M18: 2 | N18: 100-200 | O18: 1815 | P18: 3500000 | Q18: =P18*(1-28%) -> 2520000 | R18: =Q18/140 -> 18000 | S18: =Q18*M18 -> 5040000 | T18: =Q18*M18 -> 5040000 | U18: =S18+T18 -> 10080000 | V18: =U18/140 -> 72000 | W18: Ledokol Group | X18: 183505 | Y18: 99.758086 | Z18: 183950
A19: LED - экран | B19: Фото | C19: Наманган | D19: Пересечение ул.Гирвансайская и ул.А.Тимура, Ориентир Hamkorbank | E19: 6х3 | F19: 1 | G19: 2 | H19: экран | I19: динамика | J19: 1920х1080 | K19: 10 | L19: 7:00-23:00 | M19: 2 | N19: 100-200 | P19: 3500000 | Q19: =P19*(1-28%) -> 2520000 | R19: =Q19/140 -> 18000 | S19: =Q19*M19 -> 5040000 | T19: =Q19*M19 -> 5040000 | U19: =S19+T19 -> 10080000 | V19: =U19/140 -> 72000 | W19: Ledokol Group | X19: 200679 | Y19: 109.09432 | Z19: 183950
A20: LED - экран | B20: Фото | C20: Наманган | D20: перекрёсток ул.Хотира и проспекта Курумсай, ориентир Косонсой пятак | E20: 6х3 | F20: 1 | G20: 2 | H20: экран | I20: динамика | J20: 1920х1080 | K20: 10 | L20: 7:00-23:00 | M20: 2 | N20: 100-200 | P20: 3500000 | Q20: =P20*(1-28%) -> 2520000 | R20: =Q20/140 -> 18000 | S20: =Q20*M20 -> 5040000 | T20: =Q20*M20 -> 5040000 | U20: =S20+T20 -> 10080000 | V20: =U20/140 -> 72000 | W20: Ledokol Group | X20: 185663 | Y20: 100.93123 | Z20: 183950
A21: LED - экран | B21: Фото | C21: Фергана | D21: ул. Мустакиллик и Малая кольцевая дорога Ориентир ТАТУ | E21: 6х3 | F21: 1 | G21: 2 | H21: экран | I21: динамика | J21: 1920х1080 | K21: 10 | L21: 7:00-23:00 | M21: 2 | N21: 100-200 | O21: 1840 | P21: 3500000 | Q21: =P21*(1-28%) -> 2520000 | R21: =Q21/140 -> 18000 | S21: =Q21*M21 -> 5040000 | T21: =Q21*M21 -> 5040000 | U21: =S21+T21 -> 10080000 | V21: =U21/140 -> 72000 | W21: Ledokol Group | X21: 95908 | Y21: 86.139752 | Z21: 111340
A22: LED - экран | B22: Фото | C22: Фергана | D22: ул. Ахмада Яссавий и Узбекистон овози Ориентир Давр Банк | E22: 6х3 | F22: 1 | G22: 2 | H22: экран | I22: динамика | J22: 1920х1080 | K22: 10 | L22: 7:00-23:00 | M22: 2 | N22: 100-200 | O22: 109633 | P22: 3500000 | Q22: =P22*(1-28%) -> 2520000 | R22: =Q22/140 -> 18000 | S22: =Q22*M22 -> 5040000 | T22: =Q22*M22 -> 5040000 | U22: =S22+T22 -> 10080000 | V22: =U22/140 -> 72000 | W22: Ledokol Group | X22: 134679 | Y22: 120.96192 | Z22: 111340
A23: LED - экран | B23: Фото | C23: Фергана | D23: ул. Сайлох и Аль Фергани Ориентир Mobiuz | E23: 6х3 | F23: 1 | G23: 2 | H23: экран | I23: динамика | J23: 1920х1080 | K23: 10 | L23: 7:00-23:00 | M23: 2 | N23: 100-200 | O23: 7172 | P23: 3500000 | Q23: =P23*(1-28%) -> 2520000 | R23: =Q23/140 -> 18000 | S23: =Q23*M23 -> 5040000 | T23: =Q23*M23 -> 5040000 | U23: =S23+T23 -> 10080000 | V23: =U23/140 -> 72000 | W23: Ledokol Group | X23: 204642 | Y23: 183.79917 | Z23: 111340
A24: LED - экран | B24: Фото | C24: Фергана | D24: ул. А. Навои и Сохибкирон Тимура Ориентир Кинотеатр Нурхан | E24: 7х4 | F24: 1 | G24: 2 | H24: экран | I24: динамика | J24: 1920х1080 | K24: 10 | L24: 7:00-23:00 | M24: 2 | N24: 100-200 | O24: 21544 | P24: 3500000 | Q24: =P24*(1-28%) -> 2520000 | R24: =Q24/140 -> 18000 | S24: =Q24*M24 -> 5040000 | T24: =Q24*M24 -> 5040000 | U24: =S24+T24 -> 10080000 | V24: =U24/140 -> 72000 | W24: Ledokol Group | X24: 95857 | Y24: 86.093946 | Z24: 111340
A25: LED - экран | B25: Фото | C25: Фергана | D25: ул. Ватан Равнаки и Додхо Ориентир ресторан Сутан Ахмет (Зиерат) | E25: 7х4 | F25: 1 | G25: 2 | H25: экран | I25: динамика | J25: 1920х1080 | K25: 10 | L25: 7:00-23:00 | M25: 2 | N25: 100-200 | O25: 1837 | P25: 3500000 | Q25: =P25*(1-28%) -> 2520000 | R25: =Q25/140 -> 18000 | S25: =Q25*M25 -> 5040000 | T25: =Q25*M25 -> 5040000 | U25: =S25+T25 -> 10080000 | V25: =U25/140 -> 72000 | W25: Ledokol Group | X25: 100692 | Y25: 90.436501 | Z25: 111340
A26: LED - экран | B26: Фото | C26: Фергана | D26: ул. Ватан Равнаки и У.Юсупова Ориентир Центральный Рынок | E26: 7х4 | F26: 1 | G26: 2 | H26: экран | I26: динамика | J26: 1920х1080 | K26: 10 | L26: 7:00-23:00 | M26: 2 | N26: 100-200 | O26: 111140 | P26: 3500000 | Q26: =P26*(1-28%) -> 2520000 | R26: =Q26/140 -> 18000 | S26: =Q26*M26 -> 5040000 | T26: =Q26*M26 -> 5040000 | U26: =S26+T26 -> 10080000 | V26: =U26/140 -> 72000 | W26: Ledokol Group | X26: 173545 | Y26: 155.86941 | Z26: 111340
A27: LED - экран | B27: Фото | C27: Фергана | D27: ул. А. Навои и Юксалиш Ориентир Асака Банк | E27: 7х4 | F27: 1 | G27: 2 | H27: экран | I27: динамика | J27: 1920х1080 | K27: 10 | L27: 7:00-23:00 | M27: 2 | N27: 100-200 | O27: 7341 | P27: 3500000 | Q27: =P27*(1-28%) -> 2520000 | R27: =Q27/140 -> 18000 | S27: =Q27*M27 -> 5040000 | T27: =Q27*M27 -> 5040000 | U27: =S27+T27 -> 10080000 | V27: =U27/140 -> 72000 | W27: Ledokol Group | X27: 201230 | Y27: 180.73469 | Z27: 111340
A28: LED - экран | B28: Фото | C28: Фергана | D28: Малая кольцева дорога Ориентир Полвон шашлык | E28: 8х4 | F28: 1 | G28: 2 | H28: экран | I28: динамика | J28: 1920х1080 | K28: 10 | L28: 7:00-23:00 | M28: 2 | N28: 100-200 | O28: 100-201 | P28: 3500000 | Q28: =P28*(1-28%) -> 2520000 | R28: =Q28/140 -> 18000 | S28: =Q28*M28 -> 5040000 | T28: =Q28*M28 -> 5040000 | U28: =S28+T28 -> 10080000 | V28: =U28/140 -> 72000 | W28: Ledokol Group | X28: 107598 | Y28: 96.639123 | Z28: 111340
A29: LED - экран | B29: Фото | C29: Маргилан | D29: ул. Мустакиллик Ор-р: Маргиланский базар | E29: 7х4 | F29: 1 | G29: 2 | H29: экран | I29: динамика | J29: 1920х1080 | K29: 10 | L29: 7:00-23:00 | M29: 2 | N29: 100-200 | P29: 3500000 | Q29: =P29*(1-28%) -> 2520000 | R29: =Q29/140 -> 18000 | S29: =Q29*M29 -> 5040000 | T29: =Q29*M29 -> 5040000 | U29: =S29+T29 -> 10080000 | V29: =U29/140 -> 72000 | W29: Ledokol Group | X29: 111950 | Y29: 173.07752 | Z29: 64682
A30: LED - экран | B30: Фото | C30: Андижан | D30: ул. Лермонтова и Машраб Ориентир Поликлиника N5 | E30: 7х4 | F30: 1 | G30: 2 | H30: экран | I30: динамика | J30: 1920х1080 | K30: 10 | L30: 7:00-23:00 | M30: 2 | N30: 100-200 | O30: 18409 | P30: 3500000 | Q30: =P30*(1-28%) -> 2520000 | R30: =Q30/140 -> 18000 | S30: =Q30*M30 -> 5040000 | T30: =Q30*M30 -> 5040000 | U30: =S30+T30 -> 10080000 | V30: =U30/140 -> 72000 | W30: Ledokol Group | X30: 215175 | Y30: 167.64183 | Z30: 128354
A31: LED - экран | B31: Фото | C31: Андижан | D31: Проспект Бобура и ул.Машраб Ориентир СЭС, Макро | E31: 7х4 | F31: 1 | G31: 2 | H31: экран | I31: динамика | J31: 1920х1080 | K31: 10 | L31: 7:00-23:00 | M31: 2 | N31: 100-200 | O31: 1853 | P31: 3500000 | Q31: =P31*(1-28%) -> 2520000 | R31: =Q31/140 -> 18000 | S31: =Q31*M31 -> 5040000 | T31: =Q31*M31 -> 5040000 | U31: =S31+T31 -> 10080000 | V31: =U31/140 -> 72000 | W31: Ledokol Group | X31: 118383 | Y31: 92.231641 | Z31: 128354
A32: LED - экран | B32: Фото | C32: Андижан | D32: проспект Амир Темура и ул.Турон Ориентир Корзинка | E32: 7х4 | F32: 1 | G32: 2 | H32: экран | I32: динамика | J32: 1920х1080 | K32: 10 | L32: 7:00-23:00 | M32: 2 | N32: 100-200 | O32: 21542 | P32: 3500000 | Q32: =P32*(1-28%) -> 2520000 | R32: =Q32/140 -> 18000 | S32: =Q32*M32 -> 5040000 | T32: =Q32*M32 -> 5040000 | U32: =S32+T32 -> 10080000 | V32: =U32/140 -> 72000 | W32: Ledokol Group | X32: 88369 | Y32: 68.847874 | Z32: 128354
A33: LED - экран | B33: Фото | C33: Андижан | D33: ул. Узбекистанская и Бобуршох Ориентир Центр Диагностики | E33: 7х4 | F33: 1 | G33: 2 | H33: экран | I33: динамика | J33: 1920х1080 | K33: 10 | L33: 7:00-23:00 | M33: 2 | N33: 100-200 | O33: 1865 | P33: 3500000 | Q33: =P33*(1-28%) -> 2520000 | R33: =Q33/140 -> 18000 | S33: =Q33*M33 -> 5040000 | T33: =Q33*M33 -> 5040000 | U33: =S33+T33 -> 10080000 | V33: =U33/140 -> 72000 | W33: Ledokol Group | X33: 96502 | Y33: 75.184256 | Z33: 128354
A34: LED - экран | B34: Фото | C34: Андижан | D34: Ул. Дукчи Эшон, ориентир: Toshkent Premium | E34: 7х4 | F34: 1 | G34: 2 | H34: экран | I34: динамика | J34: 1920х1080 | K34: 10 | L34: 7:00-23:00 | M34: 2 | N34: 100-200 | O34: 1860 | P34: 3500000 | Q34: =P34*(1-28%) -> 2520000 | R34: =Q34/140 -> 18000 | S34: =Q34*M34 -> 5040000 | T34: =Q34*M34 -> 5040000 | U34: =S34+T34 -> 10080000 | V34: =U34/140 -> 72000 | W34: Ledokol Group | X34: 130590 | Y34: 101.74206 | Z34: 128354
A35: LED - экран | B35: Фото | C35: Андижан | D35: ул. Бобуршох | E35: 7х4 | F35: 1 | G35: 2 | H35: экран | I35: динамика | J35: 1920х1080 | K35: 10 | L35: 7:00-23:00 | M35: 2 | N35: 100-200 | O35: 7071 | P35: 3500000 | Q35: =P35*(1-28%) -> 2520000 | R35: =Q35/140 -> 18000 | S35: =Q35*M35 -> 5040000 | T35: =Q35*M35 -> 5040000 | U35: =S35+T35 -> 10080000 | V35: =U35/140 -> 72000 | W35: Ledokol Group | X35: 95203 | Y35: 74.172211 | Z35: 128354
A36: LED - экран | B36: Фото | C36: Андижан | D36: Проспект Бабура Ориентир: янги базар (3х сторонка ) | E36: 7х4 | F36: 1 | G36: 2 | H36: экран | I36: динамика | J36: 1920х1080 | K36: 10 | L36: 7:00-23:00 | M36: 2 | N36: 100-200 | O36: 18491 | P36: 5500000 | Q36: =P36*(1-28%) -> 3960000 | R36: =Q36/140 -> 28285.714 | S36: =Q36*M36 -> 7920000 | T36: =Q36*M36 -> 7920000 | U36: =S36+T36 -> 15840000 | V36: =U36/140 -> 113142.86 | W36: Ledokol Group | X36: 413770 | Y36: 322.36627 | Z36: 128354
A37: LED - экран | B37: Фото | C37: Андижан | D37: ул. А.Навои и Узбекистанская Ориентир Областной Хакимият | E37: 28х4 | F37: 1 | G37: 2 | H37: экран | I37: динамика | J37: 1920х1080 | K37: 10 | L37: 7:00-23:00 | M37: 2 | N37: 100-200 | O37: 1863 | P37: 5500000 | Q37: =P37*(1-28%) -> 3960000 | R37: =Q37/140 -> 28285.714 | S37: =Q37*M37 -> 7920000 | T37: =Q37*M37 -> 7920000 | U37: =S37+T37 -> 15840000 | V37: =U37/140 -> 113142.86 | W37: Ledokol Group | X37: 158904 | Y37: 123.80136 | Z37: 128354
A38: LED - экран | B38: Фото | C38: Самарканд | D38: ул. Абу Райхон Беруний Ориентир Старый Билайн | E38: 6х3 | F38: 1 | G38: 2 | H38: экран | I38: динамика | J38: 1920х1080 | K38: 10 | L38: 7:00-23:00 | M38: 2 | N38: 100-200 | O38: 19270 | P38: 3500000 | Q38: =P38*(1-28%) -> 2520000 | R38: =Q38/140 -> 18000 | S38: =Q38*M38 -> 5040000 | T38: =Q38*M38 -> 5040000 | U38: =S38+T38 -> 10080000 | V38: =U38/140 -> 72000 | W38: Ledokol Group | X38: 149275 | Y38: 92.882387 | Z38: 160714
A39: LED - экран | B39: Фото | C39: Самарканд | D39: ул. Дагбитская и Ибн Сино Ориентир Быв Завод ГЕЛИОН | E39: 6х3 | F39: 1 | G39: 2 | H39: экран | I39: динамика | J39: 1920х1080 | K39: 10 | L39: 7:00-23:00 | M39: 2 | N39: 100-200 | O39: 18790 | P39: 3500000 | Q39: =P39*(1-28%) -> 2520000 | R39: =Q39/140 -> 18000 | S39: =Q39*M39 -> 5040000 | T39: =Q39*M39 -> 5040000 | U39: =S39+T39 -> 10080000 | V39: =U39/140 -> 72000 | W39: Ledokol Group | X39: 156890 | Y39: 97.620618 | Z39: 160714
A40: LED - экран | B40: Фото | C40: Самарканд | D40: ул. А. Темура Ориентир Каримбек | E40: 7х4 | F40: 1 | G40: 2 | H40: экран | I40: динамика | J40: 1920х1080 | K40: 10 | L40: 7:00-23:00 | M40: 2 | N40: 100-200 | O40: 18399 | P40: 3500000 | Q40: =P40*(1-28%) -> 2520000 | R40: =Q40/140 -> 18000 | S40: =Q40*M40 -> 5040000 | T40: =Q40*M40 -> 5040000 | U40: =S40+T40 -> 10080000 | V40: =U40/140 -> 72000 | W40: Ledokol Group | X40: 193419 | Y40: 120.34981 | Z40: 160714
A41: LED - экран | B41: Фото | C41: Самарканд | D41: ул.Регистанская и ул.Дагбитская, ориентир: бывший ликёро-водочный завод | E41: 7х4 | F41: 1 | G41: 2 | H41: экран | I41: динамика | J41: 1920х1080 | K41: 10 | L41: 7:00-23:00 | M41: 2 | N41: 100-200 | O41: 21514 | P41: 3500000 | Q41: =P41*(1-28%) -> 2520000 | R41: =Q41/140 -> 18000 | S41: =Q41*M41 -> 5040000 | T41: =Q41*M41 -> 5040000 | U41: =S41+T41 -> 10080000 | V41: =U41/140 -> 72000 | W41: Ledokol Group | X41: 214655 | Y41: 133.56335 | Z41: 160714
... A49: LED - экран | B49: Фото | C49: Самарканд | D49: ул. Узбекистанская | E49: 6х3 | F49: 1 | G49: 2 | H49: экран | I49: динамика | J49: 1920х1080 | K49: 10 | L49: 7:00-23:00 | M49: 2 | N49: 100-200 | O49: 18792 | P49: 8500000 | Q49: =P49*(1-28%) -> 6120000 | R49: =Q49/140 -> 43714.286 | S49: =Q49*M49 -> 12240000 | T49: =Q49*M49 -> 12240000 | U49: =S49+T49 -> 24480000 | V49: =U49/140 -> 174857.14 | W49: Ledokol Group | X49: 279466 | Y49: 173.89026 | Z49: 160714
A50: LED - экран | B50: Фото | C50: Самарканд | D50: ул. Шахруха Мирза Ориентир ТЦ Макон Малл | E50: 10х5 | F50: 1 | G50: 2 | H50: экран | I50: динамика | J50: 1920х1080 | K50: 10 | L50: 7:00-23:00 | M50: 2 | N50: 100-200 | P50: 8500000 | Q50: =P50*(1-28%) -> 6120000 | R50: =Q50/140 -> 43714.286 | S50: =Q50*M50 -> 12240000 | T50: =Q50*M50 -> 12240000 | U50: =S50+T50 -> 24480000 | V50: =U50/140 -> 174857.14 | W50: Ledokol Group | X50: 642568 | Y50: 399.8208 | Z50: 160714
A51: LED - экран | B51: Фото | C51: Самарканд | D51: ул. Хожа Ахрор Валий Ориентир Сельский круг | E51: 28х5 | F51: 1 | G51: 2 | H51: экран | I51: динамика | J51: 1920х1080 | K51: 10 | L51: 7:00-23:00 | M51: 2 | N51: 100-200 | O51: 19506 | P51: 8500000 | Q51: =P51*(1-28%) -> 6120000 | R51: =Q51/140 -> 43714.286 | S51: =Q51*M51 -> 12240000 | T51: =Q51*M51 -> 12240000 | U51: =S51+T51 -> 24480000 | V51: =U51/140 -> 174857.14 | W51: Ledokol Group | X51: 330293 | Y51: 205.51601 | Z51: 160714
A52: LED - экран | B52: Фото | C52: Самарканд | D52: ул. Гагарина и М. Улугбека Ориентир УЗИ №1 | E52: 8х5 | F52: 1 | G52: 2 | H52: экран | I52: динамика | J52: 1920х1080 | K52: 10 | L52: 7:00-23:00 | M52: 2 | N52: 100-200 | P52: 3500000 | Q52: =P52*(1-28%) -> 2520000 | R52: =Q52/140 -> 18000 | S52: =Q52*M52 -> 5040000 | T52: =Q52*M52 -> 5040000 | U52: =S52+T52 -> 10080000 | V52: =U52/140 -> 72000 | W52: Ledokol Group | X52: 553273 | Y52: 344.25937 | Z52: 160714
A53: LED - экран | B53: Фото | C53: Бухара | D53: Проспект Навои и ул. Пиридастгир Ориентир МЕГА МАРКЕТ | E53: 7х4 | F53: 1 | G53: 2 | H53: экран | I53: динамика | J53: 1920х1080 | K53: 10 | L53: 7:00-23:00 | M53: 2 | N53: 100-200 | O53: 1749 | P53: 3500000 | Q53: =P53*(1-28%) -> 2520000 | R53: =Q53/140 -> 18000 | S53: =Q53*M53 -> 5040000 | T53: =Q53*M53 -> 5040000 | U53: =S53+T53 -> 10080000 | V53: =U53/140 -> 72000 | W53: Ledokol Group | X53: 162834 | Y53: 196.6143 | Z53: 82819
A54: LED - экран | B54: Фото | C54: Бухара | D54: ул.И.Муминова, ориентир: БГУ | E54: 8х4 | F54: 1 | G54: 2 | H54: экран | I54: динамика | J54: 1920х1080 | K54: 10 | L54: 7:00-23:00 | M54: 2 | N54: 100-200 | O54: 1738 | P54: 3500000 | Q54: =P54*(1-28%) -> 2520000 | R54: =Q54/140 -> 18000 | S54: =Q54*M54 -> 5040000 | T54: =Q54*M54 -> 5040000 | U54: =S54+T54 -> 10080000 | V54: =U54/140 -> 72000 | W54: Ledokol Group | X54: 95372 | Y54: 115.15715 | Z54: 82819
A55: LED - экран | B55: Фото | C55: Бухара | D55: ул. Намозгох Ориентир Областная Больница | E55: 8х4 | F55: 1 | G55: 2 | H55: экран | I55: динамика | J55: 1920х1080 | K55: 10 | L55: 7:00-23:00 | M55: 2 | N55: 100-200 | O55: 19614 | P55: 3500000 | Q55: =P55*(1-28%) -> 2520000 | R55: =Q55/140 -> 18000 | S55: =Q55*M55 -> 5040000 | T55: =Q55*M55 -> 5040000 | U55: =S55+T55 -> 10080000 | V55: =U55/140 -> 72000 | W55: Ledokol Group | X55: 95209 | Y55: 114.96034 | Z55: 82819
A56: LED - экран | B56: Фото | C56: Бухара | D56: ул Б. Накшбанд и Файзобод, ориентир: Моника | E56: 7х4 | F56: 1 | G56: 2 | H56: экран | I56: динамика | J56: 1920х1080 | K56: 10 | L56: 7:00-23:00 | M56: 2 | N56: 100-200 | O56: 19805 | P56: 3500000 | Q56: =P56*(1-28%) -> 2520000 | R56: =Q56/140 -> 18000 | S56: =Q56*M56 -> 5040000 | T56: =Q56*M56 -> 5040000 | U56: =S56+T56 -> 10080000 | V56: =U56/140 -> 72000 | W56: Ledokol Group | X56: 127285 | Y56: 153.69058 | Z56: 82819
A57: LED - экран | B57: Фото | C57: Бухара | D57: ул.Академика Ибрагима Муминова, ориентир: Elite Посуда | E57: 6х3 | F57: 1 | G57: 2 | H57: экран | I57: динамика | J57: 1920х1080 | K57: 10 | L57: 7:00-23:00 | M57: 2 | N57: 100-200 | O57: 18487 | P57: 3500000 | Q57: =P57*(1-28%) -> 2520000 | R57: =Q57/140 -> 18000 | S57: =Q57*M57 -> 5040000 | T57: =Q57*M57 -> 5040000 | U57: =S57+T57 -> 10080000 | V57: =U57/140 -> 72000 | W57: Ledokol Group | X57: 93333 | Y57: 112.69515 | Z57: 82819
A58: LED - экран | B58: Фото | C58: Бухара | D58: ул.Гиждуван, ориентир: Карван Базар | E58: 8х4 | F58: 1 | G58: 2 | H58: экран | I58: динамика | J58: 1920х1080 | K58: 10 | L58: 7:00-23:00 | M58: 2 | N58: 100-200 | O58: 19593 | P58: 3500000 | Q58: =P58*(1-28%) -> 2520000 | R58: =Q58/140 -> 18000 | S58: =Q58*M58 -> 5040000 | T58: =Q58*M58 -> 5040000 | U58: =S58+T58 -> 10080000 | V58: =U58/140 -> 72000 | W58: Ledokol Group | X58: 129619 | Y58: 156.50877 | Z58: 82819
A59: LED - экран | B59: Фото | C59: Бухара | D59: ул.Сулеймана Мурадова, ориентир: кафе Borжуй | E59: 6х3 | F59: 1 | G59: 2 | H59: экран | I59: динамика | J59: 1920х1080 | K59: 10 | L59: 7:00-23:00 | M59: 2 | N59: 100-200 | O59: 10320 | P59: 3500000 | Q59: =P59*(1-28%) -> 2520000 | R59: =Q59/140 -> 18000 | S59: =Q59*M59 -> 5040000 | T59: =Q59*M59 -> 5040000 | U59: =S59+T59 -> 10080000 | V59: =U59/140 -> 72000 | W59: Ledokol Group | X59: 60851 | Y59: 73.474686 | Z59: 82819
A60: LED - экран | B60: Фото | C60: Бухара | D60: ул.Ислама Каримова, ориентир: Юридический техникум | E60: 6х3 | F60: 1 | G60: 2 | H60: экран | I60: динамика | J60: 1920х1080 | K60: 10 | L60: 7:00-23:00 | M60: 2 | N60: 100-200 | O60: 1761 | P60: 3500000 | Q60: =P60*(1-28%) -> 2520000 | R60: =Q60/140 -> 18000 | S60: =Q60*M60 -> 5040000 | T60: =Q60*M60 -> 5040000 | U60: =S60+T60 -> 10080000 | V60: =U60/140 -> 72000 | W60: Ledokol Group | X60: 127156 | Y60: 153.53482 | Z60: 82819
A61: LED - экран | B61: Фото | C61: Бухара | D61: проспект ул.Бухоро и ул.М.Торобий, ориентир- Железнодорожный вокзал | E61: 6х3 | F61: 1 | G61: 2 | H61: экран | I61: динамика | J61: 1920х1080 | K61: 10 | L61: 7:00-23:00 | M61: 2 | N61: 100-200 | O61: 1764 | P61: 3500000 | Q61: =P61*(1-28%) -> 2520000 | R61: =Q61/140 -> 18000 | S61: =Q61*M61 -> 5040000 | T61: =Q61*M61 -> 5040000 | U61: =S61+T61 -> 10080000 | V61: =U61/140 -> 72000 | W61: Ledokol Group | X61: 60870 | Y61: 73.497627 | Z61: 82819
A62: LED - экран | B62: Фото | C62: Бухара | D62: ул.Ислама Каримова, ориентир- Спортивный комплекс | E62: 8х4 | F62: 1 | G62: 2 | H62: экран | I62: динамика | J62: 1920х1080 | K62: 10 | L62: 7:00-23:00 | M62: 2 | N62: 100-200 | P62: 3500000 | Q62: =P62*(1-28%) -> 2520000 | R62: =Q62/140 -> 18000 | S62: =Q62*M62 -> 5040000 | T62: =Q62*M62 -> 5040000 | U62: =S62+T62 -> 10080000 | V62: =U62/140 -> 72000 | W62: Ledokol Group | X62: 128805 | Y62: 155.52591 | Z62: 82819
A63: LED - экран | B63: Фото | C63: Карши | D63: ул. Мустакиллик и Узбекистан Ориентир Круг Курант | E63: 8х4 | F63: 1 | G63: 2 | H63: экран | I63: динамика | J63: 1920х1080 | K63: 10 | L63: 7:00-23:00 | M63: 2 | N63: 100-200 | O63: 111826 | P63: 3500000 | Q63: =P63*(1-28%) -> 2520000 | R63: =Q63/140 -> 18000 | S63: =Q63*M63 -> 5040000 | T63: =Q63*M63 -> 5040000 | U63: =S63+T63 -> 10080000 | V63: =U63/140 -> 72000 | W63: Ledokol Group | X63: 99330 | Y63: 132.15103 | Z63: 75164
A64: LED - экран | B64: Фото | C64: Карши | D64: ул. Жайхун и Насаф Ориентир Чайхана Карши | E64: 8х4 | F64: 1 | G64: 2 | H64: экран | I64: динамика | J64: 1920х1080 | K64: 10 | L64: 7:00-23:00 | M64: 2 | N64: 100-200 | O64: 19611 | P64: 3500000 | Q64: =P64*(1-28%) -> 2520000 | R64: =Q64/140 -> 18000 | S64: =Q64*M64 -> 5040000 | T64: =Q64*M64 -> 5040000 | U64: =S64+T64 -> 10080000 | V64: =U64/140 -> 72000 | W64: Ledokol Group | X64: 119479 | Y64: 158.95775 | Z64: 75164
A65: LED - экран | B65: Фото | C65: Карши | D65: ул.Насаф Ориентир Сифат | E65: 7х3 | F65: 1 | G65: 2 | H65: экран | I65: динамика | J65: 1920х1080 | K65: 10 | L65: 7:00-23:00 | M65: 2 | N65: 100-200 | O65: 8867 | P65: 3500000 | Q65: =P65*(1-28%) -> 2520000 | R65: =Q65/140 -> 18000 | S65: =Q65*M65 -> 5040000 | T65: =Q65*M65 -> 5040000 | U65: =S65+T65 -> 10080000 | V65: =U65/140 -> 72000 | W65: Ledokol Group | X65: 133444 | Y65: 177.53712 | Z65: 75164
A66: LED - экран | B66: Фото | C66: Карши | D66: ул.И.Каримова и Хашабадское Ориентир Мед Колледж | E66: 7х3 | F66: 1 | G66: 2 | H66: экран | I66: динамика | J66: 1920х1080 | K66: 10 | L66: 7:00-23:00 | M66: 2 | N66: 100-200 | O66: -56191 | P66: 3500000 | Q66: =P66*(1-28%) -> 2520000 | R66: =Q66/140 -> 18000 | S66: =Q66*M66 -> 5040000 | T66: =Q66*M66 -> 5040000 | U66: =S66+T66 -> 10080000 | V66: =U66/140 -> 72000 | W66: Ledokol Group | X66: 87719 | Y66: 116.70348 | Z66: 75164
A67: LED - экран | B67: Фото | C67: Карши | D67: ул. Узбекистан и Жайхун Ориентир Карши Малл | E67: 6х3 | F67: 1 | G67: 2 | H67: экран | I67: динамика | J67: 1920х1080 | K67: 10 | L67: 7:00-23:00 | M67: 2 | N67: 100-200 | O67: -107670.5 | P67: 3500000 | Q67: =P67*(1-28%) -> 2520000 | R67: =Q67/140 -> 18000 | S67: =Q67*M67 -> 5040000 | T67: =Q67*M67 -> 5040000 | U67: =S67+T67 -> 10080000 | V67: =U67/140 -> 72000 | W67: Ledokol Group | X67: 90838 | Y67: 120.85307 | Z67: 75164
A68: LED - экран | B68: Фото | C68: Карши | D68: Проспект Эмира Тимура Ориентир Янги Базар | E68: 6х3 | F68: 1 | G68: 2 | H68: экран | I68: динамика | J68: 1920х1080 | K68: 10 | L68: 7:00-23:00 | M68: 2 | N68: 100-200 | O68: -159150 | P68: 3500000 | Q68: =P68*(1-28%) -> 2520000 | R68: =Q68/140 -> 18000 | S68: =Q68*M68 -> 5040000 | T68: =Q68*M68 -> 5040000 | U68: =S68+T68 -> 10080000 | V68: =U68/140 -> 72000 | W68: Ledokol Group | X68: 58092 | Y68: 77.286999 | Z68: 75164
A69: LED - экран | B69: Фото | C69: Карши | D69: ул.Мустакиллик, ориентир: фабрика Санам | E69: 6х3 | F69: 1 | G69: 2 | H69: экран | I69: динамика | J69: 1920х1080 | K69: 10 | L69: 7:00-23:00 | M69: 2 | N69: 100-200 | O69: -416547.5 | P69: 3500000 | Q69: =P69*(1-28%) -> 2520000 | R69: =Q69/140 -> 18000 | S69: =Q69*M69 -> 5040000 | T69: =Q69*M69 -> 5040000 | U69: =S69+T69 -> 10080000 | V69: =U69/140 -> 72000 | W69: Ledokol Group | X69: 103604 | Y69: 137.83726 | Z69: 75164
A70: LED - экран | B70: Фото | C70: Карши | D70: Проспект Алишер Навои Ориентир Банк Ипотека | E70: 5х3 | F70: 1 | G70: 2 | H70: экран | I70: динамика | J70: 1920х1080 | K70: 10 | L70: 7:00-23:00 | M70: 2 | N70: 100-200 | O70: -468027 | P70: 3500000 | Q70: =P70*(1-28%) -> 2520000 | R70: =Q70/140 -> 18000 | S70: =Q70*M70 -> 5040000 | T70: =Q70*M70 -> 5040000 | U70: =S70+T70 -> 10080000 | V70: =U70/140 -> 72000 | W70: Ledokol Group | X70: 80027 | Y70: 106.46985 | Z70: 75164
A71: LED - экран | B71: Фото | C71: Ургенч | D71: ул. Янги Шовот Йули Ориентир ТЦ Даритал | E71: 6х3 | F71: 1 | G71: 2 | H71: экран | I71: динамика | J71: 1920х1080 | K71: 10 | L71: 7:00-23:00 | M71: 2 | N71: 100-200 | O71: -622465.5 | P71: 3500000 | Q71: =P71*(1-28%) -> 2520000 | R71: =Q71/140 -> 18000 | S71: =Q71*M71 -> 5040000 | T71: =Q71*M71 -> 5040000 | U71: =S71+T71 -> 10080000 | V71: =U71/140 -> 72000 | W71: Ledokol Group | X71: 108707 | Y71: 172.59737 | Z71: 62983
A72: LED - экран | B72: Фото | C72: Ургенч | D72: ул.П.Махмуда и Аль Хоразмий Ориентир Миллий Банк | E72: 7х4 | F72: 1 | G72: 2 | H72: экран | I72: динамика | J72: 1920х1080 | K72: 10 | L72: 7:00-23:00 | M72: 2 | N72: 100-200 | O72: -673945 | P72: 3500000 | Q72: =P72*(1-28%) -> 2520000 | R72: =Q72/140 -> 18000 | S72: =Q72*M72 -> 5040000 | T72: =Q72*M72 -> 5040000 | U72: =S72+T72 -> 10080000 | V72: =U72/140 -> 72000 | W72: Ledokol Group | X72: 76788 | Y72: 121.91861 | Z72: 62983
A73: LED - экран | B73: Фото | C73: Ургенч | D73: ул. Янги Шовом Йули и Мустакиллик Ориентир Вещевой Рынок | E73: 7х4 | F73: 1 | G73: 2 | H73: экран | I73: динамика | J73: 1920х1080 | K73: 10 | L73: 7:00-23:00 | M73: 2 | N73: 100-200 | O73: -828383.5 | P73: 3500000 | Q73: =P73*(1-28%) -> 2520000 | R73: =Q73/140 -> 18000 | S73: =Q73*M73 -> 5040000 | T73: =Q73*M73 -> 5040000 | U73: =S73+T73 -> 10080000 | V73: =U73/140 -> 72000 | W73: Ledokol Group | X73: 77183 | Y73: 122.54577 | Z73: 62983
A74: LED - экран | B74: Фото | C74: Ургенч | D74: проспект Аль Хорезми и ул. Йошлик Ориентир NBU | E74: 7х4 | F74: 1 | G74: 2 | H74: экран | I74: динамика | J74: 1920х1080 | K74: 10 | L74: 7:00-23:00 | M74: 2 | N74: 100-200 | O74: -879863 | P74: 3500000 | Q74: =P74*(1-28%) -> 2520000 | R74: =Q74/140 -> 18000 | S74: =Q74*M74 -> 5040000 | T74: =Q74*M74 -> 5040000 | U74: =S74+T74 -> 10080000 | V74: =U74/140 -> 72000 | W74: Ledokol Group | X74: 94007 | Y74: 149.25774 | Z74: 62983
... A98: LED - экран | B98: Фото | C98: Ангрен | D98: ул Навои и Мустакиллик ( Базар ) | E98: 6х3 | F98: 1 | G98: 2 | H98: экран | I98: динамика | J98: 1920х1080 | K98: 10 | L98: 7:00-23:00 | M98: 2 | N98: 100-200 | O98: -2784604.5 | P98: 3500000 | Q98: =P98*(1-28%) -> 2520000 | R98: =Q98/140 -> 18000 | S98: =Q98*M98 -> 5040000 | T98: =Q98*M98 -> 5040000 | U98: =S98+T98 -> 10080000 | V98: =U98/140 -> 72000 | W98: Ledokol Group | X98: 106919 | Y98: 202.99406 | Z98: 52671
P99: =SUM(P9:P98) -> 334000000 | Q99: =SUM(Q9:Q98) -> 240480000 | R99: =SUM(R9:R98) -> 1717714.3 | S99: =SUM(S9:S98) -> 493560000 | T99: =SUM(T9:T98) -> 493560000 | U99: =SUM(U9:U98) -> 987120000 | V99: =SUM(V9:V98) -> 7050857.1

Sheet LED Остановки 
C2: Клиент | D2: TBC
C3: Проект | D3: Размещение наружной рекламы в Узбекистане
C4: Дата | D4: 22.01.2026
A8: Тип Внешней Рекламы | B8: Фото конструкции | C8: Город | D8: Адрес расположения | E8: Размер конструкции | F8: Кол-во носителей | G8: Период размещения | H8: Тип конструкции | I8: Формат размещения | J8: Разрешение | K8: Длительность ролика | L8: Время работы | M8: Кол-во выходов в сутки | N8: id | O8: Стоимость за 1 единицу (без НДС) | P8: Цена с учетом скидки | Q8: Цена с учетом скидки в RUB | R8: Стоимость за 1 единицу (без АК и НДС) февраль | S8: Стоимость за 1 единицу (без АК и НДС) март | T8: Общая сумма (без АК и НДС) | U8: Total без НДС в RUB | V8: Подрядчик по размещению | W8: ots | X8: rating | Y8: universe
A9: Остановки | B9: Фото | C9: Самарканд | D9: ул Ибн Сино, автовокзал, юксалиш | E9: х | F9: 1 | G9: 2 | H9: led-остановка | I9: Динамика | J9: х | K9: 10 | L9: 7:00-23:00 | M9: 200-300 | N9: 8926 | O9: 2500000 | P9: =O9*(1-10%) -> 2250000 | Q9: =P9/140 -> 16071.429 | R9: =P9 -> 2250000 | S9: =P9 -> 2250000 | T9: =R9+S9 -> 4500000 | U9: =T9/140 -> 32142.857 | V9: Ledokol Group | W9: 148630 | X9: 92.481053 | Y9: 160714
A10: Остановки | C10: Самарканд | D10: ул Ибн Сино, академический лицей | E10: х | F10: 1 | G10: 2 | H10: led-остановка | I10: Динамика | J10: х | K10: 10 | L10: 7:00-23:00 | M10: 200-300 | N10: 19654 | O10: 2500000 | P10: =O10*(1-10%) -> 2250000 | Q10: =P10/140 -> 16071.429 | R10: =P10 -> 2250000 | S10: =P10 -> 2250000 | T10: =R10+S10 -> 4500000 | U10: =T10/140 -> 32142.857 | V10: Ledokol Group | W10: 130378 | X10: 81.124233 | Y10: 160714
A11: Остановки | C11: Самарканд | D11: ул Дагбитская, перекресток гелион | E11: х | F11: 1 | G11: 2 | H11: led-остановка | I11: Динамика | J11: х | K11: 10 | L11: 7:00-23:00 | M11: 200-300 | N11: 19656 | O11: 2500000 | P11: =O11*(1-10%) -> 2250000 | Q11: =P11/140 -> 16071.429 | R11: =P11 -> 2250000 | S11: =P11 -> 2250000 | T11: =R11+S11 -> 4500000 | U11: =T11/140 -> 32142.857 | V11: Ledokol Group | W11: 106836 | X11: 66.475852 | Y11: 160714
A12: Остановки | C12: Самарканд | D12: уд Дагбитская, студенческое общежитие | E12: х | F12: 1 | G12: 2 | H12: led-остановка | I12: Динамика | J12: х | K12: 10 | L12: 7:00-23:00 | M12: 200-300 | N12: 8941 | O12: 2500000 | P12: =O12*(1-10%) -> 2250000 | Q12: =P12/140 -> 16071.429 | R12: =P12 -> 2250000 | S12: =P12 -> 2250000 | T12: =R12+S12 -> 4500000 | U12: =T12/140 -> 32142.857 | V12: Ledokol Group | W12: 179366 | X12: 111.60571 | Y12: 160714
A13: Остановки | C13: Самарканд | D13: ул Бустонсарой, стадион Спартак | E13: х | F13: 1 | G13: 2 | H13: led-остановка | I13: Динамика | J13: х | K13: 10 | L13: 7:00-23:00 | M13: 200-300 | N13: 8938 | O13: 2500000 | P13: =O13*(1-10%) -> 2250000 | Q13: =P13/140 -> 16071.429 | R13: =P13 -> 2250000 | S13: =P13 -> 2250000 | T13: =R13+S13 -> 4500000 | U13: =T13/140 -> 32142.857 | V13: Ledokol Group | W13: 142832 | X13: 88.873402 | Y13: 160714
A14: Остановки | C14: Самарканд | D14: уд Дагбитская, анор банк | E14: х | F14: 1 | G14: 2 | H14: led-остановка | I14: Динамика | J14: х | K14: 10 | L14: 7:00-23:00 | M14: 200-300 | N14: 8940 | O14: 2500000 | P14: =O14*(1-10%) -> 2250000 | Q14: =P14/140 -> 16071.429 | R14: =P14 -> 2250000 | S14: =P14 -> 2250000 | T14: =R14+S14 -> 4500000 | U14: =T14/140 -> 32142.857 | V14: Ledokol Group | W14: 201796 | X14: 125.56218 | Y14: 160714
A15: Остановки | C15: Самарканд | D15: ул Рудаки, 6 баня | E15: х | F15: 1 | G15: 2 | H15: led-остановка | I15: Динамика | J15: х | K15: 10 | L15: 7:00-23:00 | M15: 200-300 | N15: 19669 | O15: 2500000 | P15: =O15*(1-10%) -> 2250000 | Q15: =P15/140 -> 16071.429 | R15: =P15 -> 2250000 | S15: =P15 -> 2250000 | T15: =R15+S15 -> 4500000 | U15: =T15/140 -> 32142.857 | V15: Ledokol Group | W15: 81458 | X15: 50.685068 | Y15: 160714
A16: Остановки | C16: Ургенч | D16: АлЬ Хорезмий, ор-р Гостиница Узбекистан | E16: х | F16: 1 | G16: 2 | H16: led-остановка | I16: Динамика | J16: х | K16: 10 | L16: 7:00-23:00 | M16: 200-300 | N16: 8928 | O16: 2300000 | P16: =O16*(1-10%) -> 2070000 | Q16: =P16/140 -> 14785.714 | R16: =P16 -> 2070000 | S16: =P16 -> 2070000 | T16: =R16+S16 -> 4140000 | U16: =T16/140 -> 29571.429 | V16: Ledokol Group | W16: 18098 | X16: 28.734738 | Y16: 62983
A17: Остановки | C17: Ургенч | D17: АлЬ Хорезмий, ор-р медиапарк | E17: х | F17: 1 | G17: 2 | H17: led-остановка | I17: Динамика | J17: х | K17: 10 | L17: 7:00-23:00 | M17: 200-300 | N17: 19652 | O17: 2300000 | P17: =O17*(1-10%) -> 2070000 | Q17: =P17/140 -> 14785.714 | R17: =P17 -> 2070000 | S17: =P17 -> 2070000 | T17: =R17+S17 -> 4140000 | U17: =T17/140 -> 29571.429 | V17: Ledokol Group | W17: 20622 | X17: 32.742169 | Y17: 62983
A18: Остановки | C18: Ургенч | D18: АлЬ Хорезмий, ор-р перекресток Бахадыр хана | E18: х | F18: 1 | G18: 2 | H18: led-остановка | I18: Динамика | J18: х | K18: 10 | L18: 7:00-23:00 | M18: 200-300 | N18: 8930 | O18: 2300000 | P18: =O18*(1-10%) -> 2070000 | Q18: =P18/140 -> 14785.714 | R18: =P18 -> 2070000 | S18: =P18 -> 2070000 | T18: =R18+S18 -> 4140000 | U18: =T18/140 -> 29571.429 | V18: Ledokol Group | W18: 18141 | X18: 28.80301 | Y18: 62983
A19: Остановки | C19: Ургенч | D19: проспект Аль Хорезмий, НБУ | E19: х | F19: 1 | G19: 2 | H19: led-остановка | I19: Динамика | J19: х | K19: 10 | L19: 7:00-23:00 | M19: 200-300 | N19: 10516 | O19: 2300000 | P19: =O19*(1-10%) -> 2070000 | Q19: =P19/140 -> 14785.714 | R19: =P19 -> 2070000 | S19: =P19 -> 2070000 | T19: =R19+S19 -> 4140000 | U19: =T19/140 -> 29571.429 | V19: Ledokol Group | W19: 25056 | X19: 39.782163 | Y19: 62983
A20: Остановки | C20: Ургенч | D20: АлЬ Хорезмий, Халк банк | E20: х | F20: 1 | G20: 2 | H20: led-остановка | I20: Динамика | J20: х | K20: 10 | L20: 7:00-23:00 | M20: 200-300 | N20: 19653 | O20: 2300000 | P20: =O20*(1-10%) -> 2070000 | Q20: =P20/140 -> 14785.714 | R20: =P20 -> 2070000 | S20: =P20 -> 2070000 | T20: =R20+S20 -> 4140000 | U20: =T20/140 -> 29571.429 | V20: Ledokol Group | W20: 18816 | X20: 29.874728 | Y20: 62983
O21: =SUM(O9:O20) -> 29000000 | P21: =SUM(P9:P20) -> 26100000 | Q21: =SUM(Q9:Q20) -> 186428.57 | R21: =SUM(R9:R20) -> 26100000 | S21: =SUM(S9:S20) -> 26100000 | T21: =SUM(T9:T20) -> 52200000 | U21: =SUM(U9:U20) -> 372857.14

Sheet Статика Таш + Регионы
C2: Клиент | D2: TBC
C3: Проект | D3: Размещение наружной рекламы в Узбекистане
C4: Дата | D4: 22.01.2026
A8: Тип Внешней Рекламы | B8: Фото конструкции | C8: Город | D8: Адрес расположения | E8: Размер конструкции | F8: Кол-во носителей | G8: Период размещения | H8: кол-во смены имиджа | I8: Тип конструкции | J8: Формат размещения (статика/ динамика) | K8: Разрешение | L8: id | M8: Стоимость за 1 единицу (без НДС) | N8: Цена с учетом скидки | O8: Цена с учетом скидки в RUB | P8: Стоимость монтажных и печатный работ ( без АК и НДС) | Q8: Стоимость за 1 единицу (без АК и НДС) февраль | R8: Стоимость за 1 единицу (без АК и НДС) март | S8: Общая сумма (без АК и НДС) | T8: Total без НДС в RUB | U8: Подрядчик по размещению | V8: ots | W8: rating | X8: universe
A9: Статика | C9: Ташкент | D9: Ул Шахриобод и ул.Богишамол , Сампи . | E9: 6х3 | F9: 1 | G9: 2 | H9: 2 | I9: билборд | J9: статика | K9: .cdr, .tif | M9: 3000000 | N9: 2800000 | O9: =N9/140 -> 20000 | P9: =1500000*H9 -> 3000000 | Q9: =N9 -> 2800000 | R9: =N9 -> 2800000 | S9: =Q9+R9+P9 -> 8600000 | T9: =S9/140 -> 61428.571 | U9: Ledokol Group
A10: Статика | C10: Ташкент | D10: Круг Учкахрамон | E10: 6х3 | F10: 1 | G10: 2 | H10: 2 | I10: билборд | J10: статика | K10: .cdr, .tif | M10: 3000000 | N10: 2800000 | O10: =N10/140 -> 20000 | P10: =1500000*H10 -> 3000000 | Q10: =N10 -> 2800000 | R10: =N10 -> 2800000 | S10: =Q10+R10+P10 -> 8600000 | T10: =S10/140 -> 61428.571 | U10: Ledokol Group
A11: Статика | C11: Ташкент | D11: Ул. Гавхар , спуск с моста , около строительного базар | E11: 6х3 | F11: 1 | G11: 2 | H11: 2 | I11: билборд | J11: статика | K11: .cdr, .tif | M11: 3000000 | N11: 2800000 | O11: =N11/140 -> 20000 | P11: =1500000*H11 -> 3000000 | Q11: =N11 -> 2800000 | R11: =N11 -> 2800000 | S11: =Q11+R11+P11 -> 8600000 | T11: =S11/140 -> 61428.571 | U11: Ledokol Group
A12: Статика | C12: Ташкент | D12: ул. Рихсили , Юнусабад Галлери | E12: 6х3 | F12: 1 | G12: 2 | H12: 2 | I12: призматрон | J12: статика | K12: .cdr, .tif | M12: 3000000 | N12: 2800000 | O12: =N12/140 -> 20000 | P12: =1500000*H12 -> 3000000 | Q12: =N12 -> 2800000 | R12: =N12 -> 2800000 | S12: =Q12+R12+P12 -> 8600000 | T12: =S12/140 -> 61428.571 | U12: Ledokol Group
A13: Статика | C13: Ташкент | D13: Ул.С.Дарваза .в сторону Ок-тепа | E13: 6х3 | F13: 1 | G13: 2 | H13: 2 | I13: билборд | J13: статика | K13: .cdr, .tif | M13: 3000000 | N13: 2800000 | O13: =N13/140 -> 20000 | P13: =1500000*H13 -> 3000000 | Q13: =N13 -> 2800000 | R13: =N13 -> 2800000 | S13: =Q13+R13+P13 -> 8600000 | T13: =S13/140 -> 61428.571 | U13: Ledokol Group
A14: Статика | C14: Ташкент | D14: Ул Саракулька , около Корзинки | E14: 6х3 | F14: 1 | G14: 2 | H14: 2 | I14: билборд | J14: статика | K14: .cdr, .tif | M14: 3000000 | N14: 2800000 | O14: =N14/140 -> 20000 | P14: =1500000*H14 -> 3000000 | Q14: =N14 -> 2800000 | R14: =N14 -> 2800000 | S14: =Q14+R14+P14 -> 8600000 | T14: =S14/140 -> 61428.571 | U14: Ledokol Group
A15: Статика | C15: Ташкент | D15: Ткад , около кафе Анхор . Сергели | E15: 6х3 | F15: 1 | G15: 2 | H15: 2 | I15: билборд | J15: статика | K15: .cdr, .tif | M15: 3000000 | N15: 2800000 | O15: =N15/140 -> 20000 | P15: =1500000*H15 -> 3000000 | Q15: =N15 -> 2800000 | R15: =N15 -> 2800000 | S15: =Q15+R15+P15 -> 8600000 | T15: =S15/140 -> 61428.571 | U15: Ledokol Group
A16: Статика | C16: Термез | D16: Ул Ибн Сино, около магазина Yashil Dunyo | E16: 6х3 | F16: 1 | G16: 2 | H16: 2 | I16: билборд | J16: статика | K16: .cdr, .tif | L16: 8 | M16: =2800000*F16 -> 2800000 | N16: =M16*(1-30%) -> 1960000 | O16: =N16/140 -> 14000 | P16: =1500000*H16 -> 3000000 | Q16: =N16 -> 1960000 | R16: =N16 -> 1960000 | S16: =Q16+R16+P16 -> 6920000 | T16: =S16/140 -> 49428.571 | U16: Ledokol Group
A17: Статика | C17: Термез | D17: Ул Ибн Сино, инденим | E17: 6х3 | F17: 1 | G17: 2 | H17: 2 | I17: билборд | J17: статика | K17: .cdr, .tif | L17: 5 | M17: =2800000*F17 -> 2800000 | N17: =M17*(1-30%) -> 1960000 | O17: =N17/140 -> 14000 | P17: =1500000*H17 -> 3000000 | Q17: =N17 -> 1960000 | R17: =N17 -> 1960000 | S17: =Q17+R17+P17 -> 6920000 | T17: =S17/140 -> 49428.571 | U17: Ledokol Group
A18: Статика | C18: Термез | D18: Ул Алишер Навои, ЦГУ | E18: 6х3 | F18: 1 | G18: 2 | H18: 2 | I18: билборд | J18: статика | K18: .cdr, .tif | L18: 8 | M18: =2800000*F18 -> 2800000 | N18: =M18*(1-30%) -> 1960000 | O18: =N18/140 -> 14000 | P18: =1500000*H18 -> 3000000 | Q18: =N18 -> 1960000 | R18: =N18 -> 1960000 | S18: =Q18+R18+P18 -> 6920000 | T18: =S18/140 -> 49428.571 | U18: Ledokol Group
A19: Статика | C19: Термез | D19: Ул Алишер Навои, стадион Сурхон | E19: 6х3 | F19: 1 | G19: 2 | H19: 2 | I19: билборд | J19: статика | K19: .cdr, .tif | L19: 5 | M19: =2800000*F19 -> 2800000 | N19: =M19*(1-30%) -> 1960000 | O19: =N19/140 -> 14000 | P19: =1500000*H19 -> 3000000 | Q19: =N19 -> 1960000 | R19: =N19 -> 1960000 | S19: =Q19+R19+P19 -> 6920000 | T19: =S19/140 -> 49428.571 | U19: Ledokol Group
A20: Статика | C20: Термез | D20: Ул Алишер Навои, около института | E20: 6х3 | F20: 1 | G20: 2 | H20: 2 | I20: билборд | J20: статика | K20: .cdr, .tif | L20: 5 | M20: =2800000*F20 -> 2800000 | N20: =M20*(1-30%) -> 1960000 | O20: =N20/140 -> 14000 | P20: =1500000*H20 -> 3000000 | Q20: =N20 -> 1960000 | R20: =N20 -> 1960000 | S20: =Q20+R20+P20 -> 6920000 | T20: =S20/140 -> 49428.571 | U20: Ledokol Group
A21: Статика | C21: Термез | D21: аэропорт | E21: 6х3 | F21: 1 | G21: 2 | H21: 2 | I21: билборд | J21: статика | K21: .cdr, .tif | L21: 5 | M21: =2800000*F21 -> 2800000 | N21: =M21*(1-30%) -> 1960000 | O21: =N21/140 -> 14000 | P21: =1500000*H21 -> 3000000 | Q21: =N21 -> 1960000 | R21: =N21 -> 1960000 | S21: =Q21+R21+P21 -> 6920000 | T21: =S21/140 -> 49428.571 | U21: Ledokol Group
A22: Статика | C22: Термез | D22: улица Истиклол, торговый центр | E22: 6х3 | F22: 1 | G22: 2 | H22: 2 | I22: билборд | J22: статика | K22: .cdr, .tif | L22: 5 | M22: =2800000*F22 -> 2800000 | N22: =M22*(1-30%) -> 1960000 | O22: =N22/140 -> 14000 | P22: =1500000*H22 -> 3000000 | Q22: =N22 -> 1960000 | R22: =N22 -> 1960000 | S22: =Q22+R22+P22 -> 6920000 | T22: =S22/140 -> 49428.571 | U22: Ledokol Group
A23: Статика | C23: Термез | D23: улица Тараккиёт, давр банк | E23: 6х3 | F23: 1 | G23: 2 | H23: 2 | I23: билборд | J23: статика | K23: .cdr, .tif | L23: 6 | M23: =2800000*F23 -> 2800000 | N23: =M23*(1-30%) -> 1960000 | O23: =N23/140 -> 14000 | P23: =1500000*H23 -> 3000000 | Q23: =N23 -> 1960000 | R23: =N23 -> 1960000 | S23: =Q23+R23+P23 -> 6920000 | T23: =S23/140 -> 49428.571 | U23: Ledokol Group
A24: Статика | C24: Бухара | D24: ул.,Алпомиш, ориентир: старая остановка ХБК | E24: 6х3 | F24: 1 | G24: 2 | H24: 2 | I24: билборд | J24: статика | K24: .cdr, .tif | L24: 8 | M24: =2800000*F24 -> 2800000 | N24: =M24*(1-30%) -> 1960000 | O24: =N24/140 -> 14000 | P24: =1500000*H24 -> 3000000 | Q24: =N24 -> 1960000 | R24: =N24 -> 1960000 | S24: =Q24+R24+P24 -> 6920000 | T24: =S24/140 -> 49428.571 | U24: Ledokol Group
A25: Статика | C25: Бухара | D25: улица Пиридастгир, бухарский колледж | E25: 6х3 | F25: 1 | G25: 2 | H25: 2 | I25: билборд | J25: статика | K25: .cdr, .tif | L25: 5 | M25: =2800000*F25 -> 2800000 | N25: =M25*(1-30%) -> 1960000 | O25: =N25/140 -> 14000 | P25: =1500000*H25 -> 3000000 | Q25: =N25 -> 1960000 | R25: =N25 -> 1960000 | S25: =Q25+R25+P25 -> 6920000 | T25: =S25/140 -> 49428.571 | U25: Ledokol Group
A26: Статика | C26: Бухара | D26: улица Бахауддина Накшбанда, Перекресток Шербудин, Горбольница, дорога в Аэропорт | E26: 6х3 | F26: 1 | G26: 2 | H26: 2 | I26: билборд | J26: статика | K26: .cdr, .tif | L26: 5 | M26: =2800000*F26 -> 2800000 | N26: =M26*(1-30%) -> 1960000 | O26: =N26/140 -> 14000 | P26: =1500000*H26 -> 3000000 | Q26: =N26 -> 1960000 | R26: =N26 -> 1960000 | S26: =Q26+R26+P26 -> 6920000 | T26: =S26/140 -> 49428.571 | U26: Ledokol Group
A27: Статика | C27: Бухара | D27: пересечение ул Ибн Сно, Афросиаб ориентир: перекресток «РАЙМАГ» | E27: 6х3 | F27: 1 | G27: 2 | H27: 2 | I27: билборд | J27: статика | K27: .cdr, .tif | L27: 5 | M27: =2800000*F27 -> 2800000 | N27: =M27*(1-30%) -> 1960000 | O27: =N27/140 -> 14000 | P27: =1500000*H27 -> 3000000 | Q27: =N27 -> 1960000 | R27: =N27 -> 1960000 | S27: =Q27+R27+P27 -> 6920000 | T27: =S27/140 -> 49428.571 | U27: Ledokol Group
... A82: Статика | C82: Наманган | D82: ул.Уйчи, гос-ца Чорсу ( мост) | E82: 6х3 | F82: 1 | G82: 2 | H82: 2 | I82: билборд | J82: статика | K82: .cdr, .tif | L82: 6 | M82: =2800000*F82 -> 2800000 | N82: =M82*(1-30%) -> 1960000 | O82: =N82/140 -> 14000 | P82: =1500000*H82 -> 3000000 | Q82: =N82 -> 1960000 | R82: =N82 -> 1960000 | S82: =Q82+R82+P82 -> 6920000 | T82: =S82/140 -> 49428.571 | U82: Ledokol Group
M83: =SUM(M9:M82) -> 208600000 | N83: =SUM(N9:N82) -> 150920000 | O83: =SUM(O9:O82) -> 1078000 | P83: =SUM(P9:P82) -> 222000000 | Q83: =SUM(Q9:Q82) -> 150920000 | R83: =SUM(R9:R82) -> 150920000 | S83: =SUM(S9:S82) -> 523840000 | T83: =SUM(T9:T82) -> 3741714.3

Sheet Аэропорт
C2: Клиент | D2: TBC
C3: Проект | D3: Размещение наружной рекламы в Узбекистане
C4: Дата | D4: 22.01.2026
A8: Тип Внешней Рекламы | B8: Фото конструкции | C8: Город | D8: Адрес расположения | E8: Размер конструкции | F8: Кол-во носителей | G8: Период размещения | H8: Тип конструкции | I8: Формат размещения (статика/ динамика) | J8: Разрешение | K8: Длительность ролика | L8: Время работы | M8: Кол-во выходов в блоке | N8: Прогнозное Кол-во выходов в сутки | O8: Стоимость за 1 единицу (без НДС) | P8: Цена с учетом скидки | Q8: Цена с учетом скидки в RUB | R8: Стоимость за 1 единицу (без АК и НДС) февраль | S8: Стоимость за 1 единицу (без АК и НДС) март | T8: Общая сумма (без АК и НДС) | U8: Total без НДС в RUB | V8: Подрядчик по размещению
A9: Аэропорт | B9: Фото | C9: Ташкент | D9: Международный аэропорт им Ислама Каримова | E9: 2560х244 | F9: 1 | G9: 2 | H9: Led экран вылет 1 | I9: динамика | J9: 1012х122 | K9: до 15 секунд | L9: круглосуточно | M9: 1 | N9: 400-500 | O9: 120000000 | P9: =O9*(1-5%) -> 114000000 | Q9: =P9/140 -> 814285.71 | R9: =P9 -> 114000000 | S9: =P9 -> 114000000 | T9: =R9+S9 -> 228000000 | U9: =T9/140 -> 1628571.4 | V9: Ledokol Group
A10: Аэропорт | B10: Фото | C10: Ташкент | E10: 1504х178 | F10: 1 | G10: 2 | H10: Led экран вылет 2 | I10: динамика | J10: 1012х122 | K10: до 15 секунд | L10: круглосуточно | M10: 1 | N10: 500-600 | O10: 107000000 | P10: 100710000 | Q10: =P10/140 -> 719357.14 | R10: =P10 -> 100710000 | S10: =P10 -> 100710000 | T10: =R10+S10 -> 201420000 | U10: =T10/140 -> 1438714.3 | V10: Ledokol Group
A11: Аэропорт | B11: Фото | C11: Самарканд | D11: Международный аэропорт | E11: 21.5х1,44 | G11: 2 | H11: Led экран терминал | J11: 8576х576 | K11: 15 секунд | L11: круглосуточно | M11: 1 | N11: 500-600 | O11: 14000000 | P11: =O11*(1-10%) -> 12600000 | Q11: =P11/140 -> 90000 | R11: =P11 -> 12600000 | S11: =P11 -> 12600000 | T11: =R11+S11 -> 25200000 | U11: =T11/140 -> 180000 | V11: Ledokol Group
A12: Аэропорт | B12: Фото | C12: Самарканд | E12: 43 дюйма | G12: 2 | H12: мониторы по всему терминалу | J12: 1920х1080 | K12: 15 секунд | L12: круглосуточно | M12: 1 | N12: 500-600 | O12: 10000000 | P12: =O12*(1-10%) -> 9000000 | Q12: =P12/140 -> 64285.714 | R12: =P12 -> 9000000 | S12: =P12 -> 9000000 | T12: =R12+S12 -> 18000000 | U12: =T12/140 -> 128571.43 | V12: Ledokol Group
O13: =SUM(O9:O12) -> 251000000 | P13: =SUM(P9:P12) -> 236310000 | Q13: =SUM(Q9:Q12) -> 1687928.6 | R13: =SUM(R9:R12) -> 236310000 | S13: =SUM(S9:S12) -> 236310000 | T13: =SUM(T9:T12) -> 472620000 | U13: =SUM(U9:U12) -> 3375857.1

Sheet Автобусы
C2: Клиент | D2: TBC
C3: Проект | D3: Размещение наружной рекламы в Узбекистане
C4: Дата | D4: 22.01.2026
A8: Тип Внешней Рекламы | B8: Фото конструкции | C8: Город | D8: Адрес расположения | E8: кол-во | F8: Кол-во носителей | G8: кол-во сены имиджа | H8: Период размещения | I8: Тип конструкции | J8: Формат размещения (статика/ динамика) | K8: Время работы | L8: Стоимость за 1 единицу (без НДС) | M8: Цена с учетом скидки | N8: Стоимость производства | O8: Цена с учетом скидки в RUB | P8: Стоимость за 1 единицу (без АК и НДС) февраль | Q8: Стоимость за 1 единицу (без АК и НДС) март | R8: Общая сумма (без АК и НДС) | S8: Total без НДС в RUB | T8: Подрядчик по размещению
A9: Автобусы | B9: Фото | C9: Самаркандская область | D9: Ташкент - Самарканд , Самарканд - Ташкент | E9: 7 | F9: 1 | G9: 2 | H9: 2 | I9: левый борт | J9: статика | K9: 4 часа 30 мин | L9: =4850000*E9 -> 33950000 | M9: =L9*(1-15%) -> 28857500 | N9: =(1000000*E9)*G9 -> 14000000 | O9: =M9/140 -> 206125 | P9: =M9 -> 28857500 | Q9: =M9 -> 28857500 | R9: =P9+Q9+N9 -> 71715000 | S9: =R9/140 -> 512250 | T9: Ledokol Group
A10: Автобусы | B10: Фото | C10: Кашкадарьинская область | D10: Ташкент - Карши , Карши - Ташкент | E10: 7 | F10: 1 | G10: 2 | H10: 2 | I10: левый борт | J10: статика | K10: 7 часов | L10: =4850000*E10 -> 33950000 | M10: =L10*(1-15%) -> 28857500 | N10: =(1000000*E10)*G10 -> 14000000 | O10: =M10/140 -> 206125 | P10: =M10 -> 28857500 | Q10: =M10 -> 28857500 | R10: =P10+Q10+N10 -> 71715000 | S10: =R10/140 -> 512250 | T10: Ledokol Group
A11: Автобусы | B11: Фото | C11: Сурхандарьинская область | D11: Ташкент - Термез , Термез - Ташкент | E11: 7 | F11: 1 | G11: 2 | H11: 2 | I11: левый борт | J11: статика | K11: 10 часов | L11: =4850000*E11 -> 33950000 | M11: =L11*(1-15%) -> 28857500 | N11: =(1000000*E11)*G11 -> 14000000 | O11: =M11/140 -> 206125 | P11: =M11 -> 28857500 | Q11: =M11 -> 28857500 | R11: =P11+Q11+N11 -> 71715000 | S11: =R11/140 -> 512250 | T11: Ledokol Group
A12: Автобусы | B12: Фото | C12: Бухарская область | D12: Ташкент - Бухара , Бухара - Ташкент | E12: 7 | F12: 1 | G12: 2 | H12: 2 | I12: левый борт | J12: статика | K12: 8 часов 50 мин | L12: =4850000*E12 -> 33950000 | M12: =L12*(1-15%) -> 28857500 | N12: =(1000000*E12)*G12 -> 14000000 | O12: =M12/140 -> 206125 | P12: =M12 -> 28857500 | Q12: =M12 -> 28857500 | R12: =P12+Q12+N12 -> 71715000 | S12: =R12/140 -> 512250 | T12: Ledokol Group
A13: Автобусы | B13: Фото | C13: Навоинская область | D13: Ташкент - Навои ,Навои - Ташкент | E13: 7 | F13: 1 | G13: 2 | H13: 2 | I13: левый борт | J13: статика | K13: 7 часов | L13: =4850000*E13 -> 33950000 | M13: =L13*(1-15%) -> 28857500 | N13: =(1000000*E13)*G13 -> 14000000 | O13: =M13/140 -> 206125 | P13: =M13 -> 28857500 | Q13: =M13 -> 28857500 | R13: =P13+Q13+N13 -> 71715000 | S13: =R13/140 -> 512250 | T13: Ledokol Group
L14: =SUM(L9:L13) -> 169750000 | M14: =SUM(M9:M13) -> 144287500 | N14: =SUM(N9:N13) -> 70000000 | O14: =SUM(O9:O13) -> 1030625 | P14: =SUM(P9:P13) -> 144287500 | Q14: =SUM(Q9:Q13) -> 144287500 | R14: =SUM(R9:R13) -> 358575000 | S14: =SUM(S9:S13) -> 2561250

Sheet Поезда
A8: Тип внешней рекламы | B8: Фото конструкции | C8: Город | D8: Адрес расположения | E8: Размер конструкции | F8: Кол-во носителей | G8: Период размещения | H8: кол-во смены имиджа | I8: Тип конструкции | J8: Разрешение | K8: Время работы | L8: Стоимость за 1 единицу ( без НДС) | M8: Стоимость за 1 ед в RUB | N8: Стоимость производства | O8: Стоимость за 1 единицу (без АК и НДС) февраль | P8: Стоимость за 1 единицу (без АК и НДС) март | Q8: Общая сумма (без АК и НДС) | R8: Total без НДС в RUB
A9: Москва 1 | B9: Фото | C9: Ташкент | D9: Ташкент Сарыагаш Оренбург Сырзань - Рязань - Москва | E9: А5 горизонтальный | F9: 180 | G9: 2 | H9: 2 | I9: Стикеры на панели | J9: А5 | K9: 2 д 18 ч 10 мин | L9: =110000*F9 -> 19800000 | M9: =L9/140 -> 141428.57 | N9: =9000000*H9 -> 18000000 | O9: =L9 -> 19800000 | P9: =L9 -> 19800000 | Q9: =L9*G9+N9 -> 57600000 | R9: =Q9/140 -> 411428.57
A10: Москва 2 | C10: Ташкент | D10: Ташкент Сарыагаш Оренбург Сырзань - Рязань - Москва | E10: А5 горизонтальный | F10: 180 | G10: 2 | H10: 2 | I10: Стикеры на панели | J10: А5 | K10: 2 д 18 ч 10 мин | L10: =110000*F10 -> 19800000 | M10: =L10/140 -> 141428.57 | N10: =9000000*H10 -> 18000000 | O10: =L10 -> 19800000 | P10: =L10 -> 19800000 | Q10: =L10*G10+N10 -> 57600000 | R10: =Q10/140 -> 411428.57
A11: Ledokol x Golden House 2025 final.xlsx | L11: =SUM(L9:L10) -> 39600000 | M11: =SUM(M9:M10) -> 282857.14 | N11: =SUM(N9:N10) -> 36000000 | O11: =SUM(O9:O10) -> 39600000 | P11: =SUM(P9:P10) -> 39600000 | Q11: =SUM(Q9:Q10) -> 115200000 | R11: =SUM(R9:R10) -> 822857.14
P14: Total без АК и НДС | Q14: =Q11 -> 115200000
P15: АК 5% | Q15: =Q14*5% -> 5760000
P16: Итоговая сумма | Q16: =(Q14+Q15)*1.12 -> 135475200

Sheet регионы-города
A1: ГМ/СМ | B1: Город присутствия Ленты | C1: Дивизион
A2: ГМ | B2: Самара | C2: Волга
A3: ГМ | B3: Тольятти | C3: Волга
A4: ГМ | B4: Димитровград | C4: Волга
A5: ГМ | B5: Ульяновск | C5: Волга
A6: ГМ | B6: Саранск | C6: Волга
A7: ГМ | B7: Чебоксары | C7: Волга
A8: ГМ | B8: Йошкар-Ола | C8: Волга
A9: ГМ | B9: Казань | C9: Волга
A10: ГМ | B10: Альметьевск | C10: Волга
A11: ГМ | B11: Набережные Челны | C11: Волга
A12: ГМ | B12: Нижнекамск | C12: Волга
... A154: СМ | B154: Химки (Сходня) | C154: Центр_ДМФ

Sheet справочник
A1: ГМ | B1: навигация | C1: статика | D1: да | E1: тендер | F1: навигационные знаки | G1: статика
A2: СМ | B2: охват | C2: динамика | D2: нет | E2: добор | F2: indoor | G2: динамика
A3: Мини | F3: транспорт
